stitch_n_split/__init__.py
stitch_n_split/geo_info.py
stitch_n_split/utility.py
stitch_n_split/split/__init__.py
stitch_n_split/split/images.py
stitch_n_split/split/mesh.py
stitch_n_split/stitch/__init__.py
stitch_n_split/stitch/images.py
stitch_n_split-0.1.2.dist-info/LICENSE
stitch_n_split-0.1.2.dist-info/METADATA
stitch_n_split-0.1.2.dist-info/WHEEL
stitch_n_split-0.1.2.dist-info/top_level.txt
stitch_n_split-0.1.2.dist-info/RECORD
