Metadata-Version: 2.1
Name: stitch-n-split
Version: 0.1.2
Summary: Library for stitching and spliting
Author: Fuzail Palnak
Author-email: fuzailpalnak@gmail.com
Keywords: GIS Rasterio Sticth Split Mesh Grid Geo Reference
Classifier: Programming Language :: Python :: 3
Classifier: License :: OSI Approved :: MIT License
Classifier: Operating System :: OS Independent
Requires-Python: ~=3.3
License-File: LICENSE
Requires-Dist: opencv-python (>=4.1.1)
Requires-Dist: affine (>=2.3.0)
Requires-Dist: numpy
Requires-Dist: image-fragment (>=0.2.2)
